imdataset-tool/__init__.py
imdataset-tool/paths.py
imdataset_tool/__init__.py
imdataset_tool/paths.py
imdataset_tool-0.0.3.dist-info/METADATA
imdataset_tool-0.0.3.dist-info/RECORD
imdataset_tool-0.0.3.dist-info/WHEEL
imdataset_tool-0.0.3.dist-info/top_level.txt
