Metadata-Version: 2.1
Name: imdataset-tool
Version: 0.0.3
Summary: a tool helps programmer to manage dataset of cv project
Home-page: UNKNOWN
Author: kathy.chen
Author-email: v_xchen_v@pku.edu.cn
License: UNKNOWN
Platform: UNKNOWN
